Workbook
Name Aporte: 'Simulador Financeiro'!$D$18
Name Dividendos: 'Simulador Financeiro'!$D$22
Name Invest_Mensal: 'Simulador Financeiro'!$D$33
Name Patrimonio: 'Simulador Financeiro'!$D$21
Name Quant_Anos: 'Simulador Financeiro'!$D$19
Name Rendimento_Carteira: 'Simulador Financeiro'!$D$14
Name Salario: 'Simulador Financeiro'!$D$13
Name Sugestao_Invest: 'Simulador Financeiro'!$D$15
Name Taxa_Mensal: 'Simulador Financeiro'!$D$20

Sheet Simulador Financeiro
B12: CONFIGURAÇÕES
B13: Salário | D13: 2000
B14: Rendimento Carteira | D14: 0.006
B15: Sugestãode Investimento (30%) | D15: =D13*30% -> 600
B17: INVESTIMENTO MENSAL
B18: Quanto investir por mês? | D18: 200
B19: Quantos anos devo investir? | D19: 5
B20: Taxa de rendimento mensal? | D20: 0.01079
B21: Patrimonio acumulado? | D21: =FV(Taxa_Mensal,Quant_Anos*12,Aporte)*-1 -> 16755.383
B22: Dividendos mensais? | D22: =Patrimonio*Rendimento_Carteira -> 100.5323
B24: CENÁRIOS | D24: DIVIDENDOS
A25: 2 | B25: Quanto em 2 anos? | C25: =FV($D$20,$A25*12,$D$18)*-1 -> 5445.5255 | D25: =C25*Rendimento_Carteira -> 32.673153
A26: 5 | B26: Quanto em 5 anos? | C26: =FV($D$20,$A26*12,$D$18)*-1 -> 16755.383 | D26: =C26*Rendimento_Carteira -> 100.5323
A27: 10 | B27: Quanto em 10 anos? | C27: =FV($D$20,$A27*12,$D$18)*-1 -> 48656.843 | D27: =C27*Rendimento_Carteira -> 291.94106
A28: 20 | B28: Quanto em 20 anos? | C28: =FV($D$20,$A28*12,$D$18)*-1 -> 225039.68 | D28: =C28*Rendimento_Carteira -> 1350.2381
A29: 30 | B29: Quanto em 30 anos? | C29: =FV($D$20,$A29*12,$D$18)*-1 -> 864433.93 | D29: =C29*Rendimento_Carteira -> 5186.6036
B32: PERFIL | D32: MODERADO
B33: VALOR A SER INVESTIDO POR MÊS | D33: =Aporte -> 200
B35: TIPO DE FII | C35: PERCENTUAL SUGERIDO | D35: VALORES
B36: PAPEL | C36: =VLOOKUP($D$32&"-"&B36,Tabela_Apoio!B:E,4,0) -> 0.32 | D36: =$C36*$D$33 -> 64
B37: TIJOLO | C37: =VLOOKUP($D$32&"-"&B37,Tabela_Apoio!B:E,4,0) -> 0.35 | D37: =$C37*$D$33 -> 70
B38: HÍBRIDOS | C38: =VLOOKUP($D$32&"-"&B38,Tabela_Apoio!B:E,4,0) -> 0.08 | D38: =$C38*$D$33 -> 16
B39: FOFs | C39: =VLOOKUP($D$32&"-"&B39,Tabela_Apoio!B:E,4,0) -> 0.1 | D39: =$C39*$D$33 -> 20
B40: DESENVOLVIMENTOS | C40: =VLOOKUP($D$32&"-"&B40,Tabela_Apoio!B:E,4,0) -> 0.05 | D40: =$C40*$D$33 -> 10
B41: HOTELARIAS | C41: =VLOOKUP($D$32&"-"&B41,Tabela_Apoio!B:E,4,0) -> 0.1 | D41: =$C41*$D$33 -> 20
B42: TOTAL | C42: =SUM(C36:C41) -> 1 | D42: =SUM(D36:D41) -> 200

Sheet Tabela_Apoio
B2: Chave Composta | C2: Perfil | D2: TIPO DE FII | E2: %
B3: =$C3&"-"&$D3 -> CONSERVADOR-PAPEL | C3: CONSERVADOR | D3: PAPEL | E3: 0.3
B4: =$C4&"-"&$D4 -> CONSERVADOR-TIJOLO | C4: CONSERVADOR | D4: TIJOLO | E4: 0.5
B5: =$C5&"-"&$D5 -> CONSERVADOR-HÍBRIDOS | C5: CONSERVADOR | D5: HÍBRIDOS | E5: 0.1
B6: =$C6&"-"&$D6 -> CONSERVADOR-FOFs | C6: CONSERVADOR | D6: FOFs | E6: 0.1
B7: =$C7&"-"&$D7 -> CONSERVADOR-DESENVOLVIMENTOS | C7: CONSERVADOR | D7: DESENVOLVIMENTOS | E7: 0
B8: =$C8&"-"&$D8 -> CONSERVADOR-HOTELARIAS | C8: CONSERVADOR | D8: HOTELARIAS | E8: 0
B9: =$C9&"-"&$D9 -> MODERADO-PAPEL | C9: MODERADO | D9: PAPEL | E9: 0.32
B10: =$C10&"-"&$D10 -> MODERADO-TIJOLO | C10: MODERADO | D10: TIJOLO | E10: 0.35
B11: =$C11&"-"&$D11 -> MODERADO-HÍBRIDOS | C11: MODERADO | D11: HÍBRIDOS | E11: 0.08
B12: =$C12&"-"&$D12 -> MODERADO-FOFs | C12: MODERADO | D12: FOFs | E12: 0.1
B13: =$C13&"-"&$D13 -> MODERADO-DESENVOLVIMENTOS | C13: MODERADO | D13: DESENVOLVIMENTOS | E13: 0.05
B14: =$C14&"-"&$D14 -> MODERADO-HOTELARIAS | C14: MODERADO | D14: HOTELARIAS | E14: 0.1
... B20: =$C20&"-"&$D20 -> AGRESSIVO-HOTELARIAS | C20: AGRESSIVO | D20: HOTELARIAS | E20: 0.1
